vimgolf/__main__.py
vimgolf/html.py
vimgolf/keys.py
vimgolf/version.txt
vimgolf/vimgolf.py
vimgolf/vimgolf.vimrc
vimgolf-0.5.3.dist-info/licenses/LICENSE
vimgolf-0.5.3.dist-info/METADATA
vimgolf-0.5.3.dist-info/WHEEL
vimgolf-0.5.3.dist-info/entry_points.txt
vimgolf-0.5.3.dist-info/top_level.txt
vimgolf-0.5.3.dist-info/RECORD
